_portaudio.cpython-37m-x86_64-linux-gnu.so
outport-4.dist-info/entry_points.txt
outport-4.dist-info/METADATA
outport-4.dist-info/COPYING
outport-4.dist-info/WHEEL
outport-4.dist-info/top_level.txt
outport-4.dist-info/LICENSE.pyaudio
outport-4.dist-info/RECORD
outport/__init__.py
