Metadata-Version: 2.1
Name: outport
Version: 4
Summary: Fork of PyAudio that ships manylinux wheels
Home-page: https://github.com/combatopera/outport
Author: Andrzej Cichocki
License: UNKNOWN
Platform: UNKNOWN
